Week 4/icarus_code/Mycounter.v
module Mycounter(CLK,RST,OUT);
	input CLK,RST;
	output reg [3:0]OUT;
	
	always @(posedge CLK)begin
		if(RST == 1'b1)
			OUT<= 4'b0000;
		else
			OUT <= OUT +1;
	end
endmodule

Week 4/icarus_code/Testbench.v
`timescale 1ns/1ps
module Testbench();

    reg Clock = 0;   // initialize here ONLY
    reg Reset;
    wire [3:0] Count;

    Mycounter I1(.CLK(Clock), .RST(Reset), .OUT(Count));

    always #50 Clock = ~Clock;

    initial begin
        $dumpfile("count.vcd");
        $dumpvars(0, Testbench);

        Reset = 1'b1;
        #100 Reset = 1'b0;

        #2000 Reset = 1'b1;
        #400 $finish;
    end

endmodule

Week 4/icarus_code/count.vcd
$date
	Sat May  2 10:58:19 2026
$end
$version
	Icarus Verilog
$end
$timescale
	1ps
$end
$scope module Testbench $end
$var wire 4 ! Count [3:0] $end
$var reg 1 " Clock $end
$var reg 1 # Reset $end
$scope module I1 $end
$var wire 1 " CLK $end
$var wire 1 # RST $end
$var reg 4 $ OUT [3:0] $end
$upscope $end
$upscope $end
$enddefinitions $end
$dumpall
$end
#0
$dumpvars
bx $
1#
0"
bx !
$end
#50000
b0 !
b0 $
1"
#100000
0"
0#
#150000
b1 !
b1 $
1"
#200000
0"
#250000
b10 !
b10 $
1"
#300000
0"
#350000
b11 !
b11 $
1"
#400000
0"
#450000
b100 !
b100 $
1"
#500000
0"
#550000
b101 !
b101 $
1"
#600000
0"
#650000
b110 !
b110 $
1"
#700000
0"
#750000
b111 !
b111 $
1"
#800000
0"
#850000
b1000 !
b1000 $
1"
#900000
0"
#950000
b1001 !
b1001 $
1"
#1000000
0"
#1050000
b1010 !
b1010 $
1"
#1100000
0"
#1150000
b1011 !
b1011 $
1"
#1200000
0"
#1250000
b1100 !
b1100 $
1"
#1300000
0"
#1350000
b1101 !
b1101 $
1"
#1400000
0"
#1450000
b1110 !
b1110 $
1"
#1500000
0"
#1550000
b1111 !
b1111 $
1"
#1600000
0"
#1650000
b0 !
b0 $
1"
#1700000
0"
#1750000
b1 !
b1 $
1"
#1800000
0"
#1850000
b10 !
b10 $
1"
#1900000
0"
#1950000
b11 !
b11 $
1"
#2000000
0"
#2050000
b100 !
b100 $
1"
#2100000
0"
1#
#2150000
b0 !
b0 $
1"
